{
  "utenti": [
    {
      "firstName": "guest",
      "lastName": "guest",
      "email": "root@root.it",
      "birthDate": "1000-10-10",
      "password": "Root123!",
      "id": 1
    }
  ],
  "conti": [
    {
      "numero_conto": 14,
      "saldo": 2000,
      "attivo": true,
      "idUt": 1,
      "id": 1
    }
  ],
  "richieste": [],
  "transazioni": [
    {
      "type": "deposit",
      "date": "Wed Jun 15 2022",
      "amount": 1000,
      "description": "Deposit",
      "idConto": 1,
      "id": 1
    },
    {
      "type": "deposit",
      "date": "Wed Jun 15 2022",
      "amount": 1000,
      "description": "Deposit",
      "idConto": 1,
      "id": 2
    }
  ],
  "dipendenti": [
    {
      "email": "homersimpson@dipendente.it",
      "password": "ciambelle",
      "id": 0
    }
  ]
}